MANIFEST.in
README.rst
setup.py
collective/__init__.py
collective.portlet.localcontents.egg-info/PKG-INFO
collective.portlet.localcontents.egg-info/SOURCES.txt
collective.portlet.localcontents.egg-info/dependency_links.txt
collective.portlet.localcontents.egg-info/entry_points.txt
collective.portlet.localcontents.egg-info/namespace_packages.txt
collective.portlet.localcontents.egg-info/not-zip-safe
collective.portlet.localcontents.egg-info/requires.txt
collective.portlet.localcontents.egg-info/top_level.txt
collective/portlet/__init__.py
collective/portlet/localcontents/__init__.py
collective/portlet/localcontents/configure.zcml
collective/portlet/localcontents/i18n.sh
collective/portlet/localcontents/localcontents.pt
collective/portlet/localcontents/localcontents.py
collective/portlet/localcontents/locales/collective.portlet.localcontents.pot
collective/portlet/localcontents/locales/it/LC_MESSAGES/collective.portlet.localcontents.po
collective/portlet/localcontents/profiles/default/metadata.xml
collective/portlet/localcontents/profiles/default/portlets.xml
collective/portlet/localcontents/tests/__init__.py
collective/portlet/localcontents/tests/base.py
collective/portlet/localcontents/tests/test_portlet.py
docs/HISTORY.txt
docs/INSTALL.txt
docs/LICENSE.GPL
docs/LICENSE.txt