Metadata-Version: 1.1
Name: collective.portlet.localcontents
Version: 0.3.0
Summary: A local navigation for Plone, that shows only contents in current folder
Home-page: http://plone.org/products/collective.portlet.localcontents
Author: RedTurtle Technology
Author-email: sviluppoplone@redturtle.it
License: GPL
Keywords: plone portlet navigation
Platform: UNKNOWN
Classifier: Framework :: Plone
Classifier: Framework :: Plone :: 3.3
Classifier: Framework :: Plone :: 4.0
Classifier: Framework :: Plone :: 4.2
Classifier: Programming Language :: Python
Classifier: Development Status :: 4 - Beta
